gerrytools/__init__.py
gerrytools/ben/__init__.py
gerrytools/ben/binary_ensemble.py
gerrytools/ben/docker_manager.py
gerrytools/ben/parse.py
gerrytools/ben/reben.py
gerrytools/data/AssignmentCompressor.py
gerrytools/data/URLs.py
gerrytools/data/__init__.py
gerrytools/data/acs.py
gerrytools/data/census.py
gerrytools/data/estimatecvap.py
gerrytools/data/fetch.py
gerrytools/data/geometries.py
gerrytools/data/remap.py
gerrytools/geometry/__init__.py
gerrytools/geometry/compactness.py
gerrytools/geometry/dataframe.py
gerrytools/geometry/dissolve.py
gerrytools/geometry/dualgraph.py
gerrytools/geometry/optimize.py
gerrytools/geometry/unitmap.py
gerrytools/geometry/updater.py
gerrytools/mgrp/__init__.py
gerrytools/mgrp/run_container.py
gerrytools/mgrp/runners/__init__.py
gerrytools/mgrp/runners/forest.py
gerrytools/mgrp/runners/recom.py
gerrytools/mgrp/runners/smc.py
gerrytools/plotting/__init__.py
gerrytools/plotting/annotation.py
gerrytools/plotting/bins.py
gerrytools/plotting/boxplot.py
gerrytools/plotting/choropleth.py
gerrytools/plotting/colors.py
gerrytools/plotting/districtnumbers.py
gerrytools/plotting/drawgraph.py
gerrytools/plotting/drawplan.py
gerrytools/plotting/gifs.py
gerrytools/plotting/histogram.py
gerrytools/plotting/latexcolors.json
gerrytools/plotting/multidimensional.py
gerrytools/plotting/scatterplot.py
gerrytools/plotting/sealevel.py
gerrytools/plotting/utils.py
gerrytools/plotting/violin.py
gerrytools/scoring/__init__.py
gerrytools/scoring/contiguity.py
gerrytools/scoring/demographics.py
gerrytools/scoring/partisan.py
gerrytools/scoring/population.py
gerrytools/scoring/scores.py
gerrytools/scoring/splits.py
gerrytools/scoring/types.py
gerrytools/utilities/JSON.py
gerrytools/utilities/__init__.py
gerrytools/utilities/rename.py
gerrytools-1.2.1.dist-info/licenses/LICENSE
gerrytools-1.2.1.dist-info/METADATA
gerrytools-1.2.1.dist-info/WHEEL
gerrytools-1.2.1.dist-info/top_level.txt
gerrytools-1.2.1.dist-info/RECORD
