Metadata-Version: 2.4
Name: gerrytools
Version: 1.2.1
Summary: Tools for processing and visualizing districting plans.
Author-email: MGGG Redistricting Lab <engineering@mggg.org>
License: MIT
Requires-Python: >=3.11
License-File: LICENSE
Requires-Dist: pandas>=2.3.2
Requires-Dist: scipy>=1.16.1
Requires-Dist: networkx>=3.5.0
Requires-Dist: geopandas>=1.1.1
Requires-Dist: Shapely>=2.0.0
Requires-Dist: matplotlib>=3.10.6
Requires-Dist: gerrychain>=0.3.2
Requires-Dist: sortedcontainers
Requires-Dist: jsonlines>=4.0.0
Requires-Dist: imageio>=2.37.0
Requires-Dist: us>=3.2.0
Requires-Dist: pydantic>=2.11.7
Requires-Dist: censusdata>=1.15.post1
Requires-Dist: seaborn>=0.13.2
Requires-Dist: numpy>=2.3.2
Requires-Dist: maup>=2.0.3
Requires-Dist: gurobipy>=12.0.3
Requires-Dist: opencv-python-headless>=4.11.0.86
Provides-Extra: docs
Requires-Dist: myst-parser>=4.0.1; extra == "docs"
Requires-Dist: sphinx>=8.2.3; extra == "docs"
Requires-Dist: sphinx-copybutton>=0.5.2; extra == "docs"
Requires-Dist: sphinx-rtd-theme>=3.0.2; extra == "docs"
Dynamic: license-file
